eff_uper.py
eff_uper-0.0.5.dist-info/METADATA
eff_uper-0.0.5.dist-info/WHEEL
eff_uper-0.0.5.dist-info/entry_points.txt
eff_uper-0.0.5.dist-info/top_level.txt
eff_uper-0.0.5.dist-info/RECORD
