Metadata-Version: 2.1
Name: eff-uper
Version: 0.0.5
Summary: Numerical values used to evaluate the contribution of basketball players in the B1 League (2016-2021) Python Package to compare "EFF" and "uPER" by year
Home-page: https://github.com/haku-19/eff_uper.git
Author: Miu Takahashi
Author-email: s2022046@stu.musashino-u.ac.jp
License: UNKNOWN
Project-URL: Bug Tracker, https://github.com/haku-19/eff_uper.git
Platform: UNKNOWN
Classifier: Programming Language :: Python :: 3
Classifier: License :: OSI Approved :: MIT License
Classifier: Operating System :: OS Independent
Requires-Python: >=3.7
